[
  { "symbol": "AFG", "name": "Afghan" },
  { "symbol": "ALB", "name": "Albanian" },
  { "symbol": "DZA", "name": "Algerian" },
  { "symbol": "ASM", "name": "American Samoan" },
  { "symbol": "AND", "name": "Andorran" },
  { "symbol": "AGO", "name": "Angolan" },
  { "symbol": "AIA", "name": "Anguillan" },
  { "symbol": "ATA", "name": "Antarctic" },
  { "symbol": "ATG", "name": "Antiguan" },
  { "symbol": "ARG", "name": "Argentine" },
  { "symbol": "ARM", "name": "Armenian" },
  { "symbol": "ABW", "name": "Aruban" },
  { "symbol": "AUS", "name": "Australian" },
  { "symbol": "AUT", "name": "Austrian" },
  { "symbol": "AZE", "name": "Azerbaijani" },
  { "symbol": "BHS", "name": "Bahamian" },
  { "symbol": "BHR", "name": "Bahraini" },
  { "symbol": "BGD", "name": "Bangladeshi" },
  { "symbol": "BRB", "name": "Barbadian" },
  { "symbol": "BLR", "name": "Belarusian" },
  { "symbol": "BEL", "name": "Belgian" },
  { "symbol": "BLZ", "name": "Belizean" },
  { "symbol": "BEN", "name": "Beninese" },
  { "symbol": "BMU", "name": "Bermudian" },
  { "symbol": "BTN", "name": "Bhutanese" },
  { "symbol": "BOL", "name": "Bolivian" },
  { "symbol": "BES", "name": "Bonaire Islander" },
  { "symbol": "BIH", "name": "Bosnian" },
  { "symbol": "BWA", "name": "Botswanan" },
  { "symbol": "BVT", "name": "Bouvet Islander" },
  { "symbol": "BRA", "name": "Brazilian" },
  { "symbol": "IOT", "name": "British Indian Ocean Territory" },
  { "symbol": "BRN", "name": "Bruneian" },
  { "symbol": "BGR", "name": "Bulgarian" },
  { "symbol": "BFA", "name": "Burkinabe" },
  { "symbol": "BDI", "name": "Burundian" },
  { "symbol": "CPV", "name": "Cape Verdean" },
  { "symbol": "KHM", "name": "Cambodian" },
  { "symbol": "CMR", "name": "Cameroonian" },
  { "symbol": "CAN", "name": "Canadian" },
  { "symbol": "CYM", "name": "Caymanian" },
  { "symbol": "CAF", "name": "Central African" },
  { "symbol": "TCD", "name": "Chadian" },
  { "symbol": "CHL", "name": "Chilean" },
  { "symbol": "CHN", "name": "Chinese" },
  { "symbol": "CXR", "name": "Christmas Islander" },
  { "symbol": "CCK", "name": "Cocos Islander" },
  { "symbol": "COL", "name": "Colombian" },
  { "symbol": "COM", "name": "Comorian" },
  { "symbol": "COG", "name": "Congolese" },
  { "symbol": "COD", "name": "Congolese" },
  { "symbol": "COK", "name": "Cook Islander" },
  { "symbol": "CRI", "name": "Costa Rican" },
  { "symbol": "CIV", "name": "Ivorian" },
  { "symbol": "HRV", "name": "Croatian" },
  { "symbol": "CUB", "name": "Cuban" },
  { "symbol": "CUW", "name": "Curacaoan" },
  { "symbol": "CYP", "name": "Cypriot" },
  { "symbol": "CZE", "name": "Czech" },
  { "symbol": "DNK", "name": "Danish" },
  { "symbol": "DJI", "name": "Djiboutian" },
  { "symbol": "DMA", "name": "Dominican" },
  { "symbol": "DOM", "name": "Dominican" },
  { "symbol": "ECU", "name": "Ecuadorian" },
  { "symbol": "EGY", "name": "Egyptian" },
  { "symbol": "SLV", "name": "Salvadoran" },
  { "symbol": "GNQ", "name": "Equatorial Guinean" },
  { "symbol": "ERI", "name": "Eritrean" },
  { "symbol": "EST", "name": "Estonian" },
  { "symbol": "SWZ", "name": "Swazi" },
  { "symbol": "ETH", "name": "Ethiopian" },
  { "symbol": "FLK", "name": "Falkland Islander" },
  { "symbol": "FRO", "name": "Faroese" },
  { "symbol": "FJI", "name": "Fijian" },
  { "symbol": "FIN", "name": "Finnish" },
  { "symbol": "FRA", "name": "French" },
  { "symbol": "GUF", "name": "French Guianese" },
  { "symbol": "PYF", "name": "French Polynesian" },
  { "symbol": "ATF", "name": "French Southern Territories" },
  { "symbol": "GAB", "name": "Gabonese" },
  { "symbol": "GMB", "name": "Gambian" },
  { "symbol": "GEO", "name": "Georgian" },
  { "symbol": "DEU", "name": "German" },
  { "symbol": "GHA", "name": "Ghanaian" },
  { "symbol": "GIB", "name": "Gibraltarian" },
  { "symbol": "GRC", "name": "Greek" },
  { "symbol": "GRL", "name": "Greenlandic" },
  { "symbol": "GRD", "name": "Grenadian" },
  { "symbol": "GLP", "name": "Guadeloupean" },
  { "symbol": "GUM", "name": "Guamanian" },
  { "symbol": "GTM", "name": "Guatemalan" },
  { "symbol": "GGY", "name": "Guernsey" },
  { "symbol": "GIN", "name": "Guinean" },
  { "symbol": "GNB", "name": "Guinea-Bissauan" },
  { "symbol": "GUY", "name": "Guyanese" },
  { "symbol": "HTI", "name": "Haitian" },
  { "symbol": "HMD", "name": "Heard Islander" },
  { "symbol": "VAT", "name": "Vatican" },
  { "symbol": "HND", "name": "Honduran" },
  { "symbol": "HKG", "name": "Hong Konger" },
  { "symbol": "HUN", "name": "Hungarian" },
  { "symbol": "ISL", "name": "Icelandic" },
  { "symbol": "IND", "name": "Indian" },
  { "symbol": "IDN", "name": "Indonesian" },
  { "symbol": "IRN", "name": "Iranian" },
  { "symbol": "IRQ", "name": "Iraqi" },
  { "symbol": "IRL", "name": "Irish" },
  { "symbol": "IMN", "name": "Manx" },
  { "symbol": "ISR", "name": "Israeli" },
  { "symbol": "ITA", "name": "Italian" },
  { "symbol": "JAM", "name": "Jamaican" },
  { "symbol": "JPN", "name": "Japanese" },
  { "symbol": "JEY", "name": "Jersey" },
  { "symbol": "JOR", "name": "Jordanian" },
  { "symbol": "KAZ", "name": "Kazakhstani" },
  { "symbol": "KEN", "name": "Kenyan" },
  { "symbol": "KIR", "name": "I-Kiribati" },
  { "symbol": "PRK", "name": "North Korean" },
  { "symbol": "KOR", "name": "South Korean" },
  { "symbol": "KWT", "name": "Kuwaiti" },
  { "symbol": "KGZ", "name": "Kyrgyzstani" },
  { "symbol": "LAO", "name": "Laotian" },
  { "symbol": "LVA", "name": "Latvian" },
  { "symbol": "LBN", "name": "Lebanese" },
  { "symbol": "LSO", "name": "Lesotho" },
  { "symbol": "LBR", "name": "Liberian" },
  { "symbol": "LBY", "name": "Libyan" },
  { "symbol": "LIE", "name": "Liechtensteiner" },
  { "symbol": "LTU", "name": "Lithuanian" },
  { "symbol": "LUX", "name": "Luxembourgish" },
  { "symbol": "MAC", "name": "Macanese" },
  { "symbol": "MKD", "name": "Macedonian" },
  { "symbol": "MDG", "name": "Malagasy" },
  { "symbol": "MWI", "name": "Malawian" },
  { "symbol": "MYS", "name": "Malaysian" },
  { "symbol": "MDV", "name": "Maldivian" },
  { "symbol": "MLI", "name": "Malian" },
  { "symbol": "MLT", "name": "Maltese" },
  { "symbol": "MHL", "name": "Marshallese" },
  { "symbol": "MTQ", "name": "Martinican" },
  { "symbol": "MRT", "name": "Mauritanian" },
  { "symbol": "MUS", "name": "Mauritian" },
  { "symbol": "MYT", "name": "Mahoran" },
  { "symbol": "MEX", "name": "Mexican" },
  { "symbol": "FSM", "name": "Micronesian" },
  { "symbol": "MDA", "name": "Moldovan" },
  { "symbol": "MCO", "name": "Monégasque" },
  { "symbol": "MNG", "name": "Mongolian" },
  { "symbol": "MNE", "name": "Montenegrin" },
  { "symbol": "MSR", "name": "Montserratian" },
  { "symbol": "MAR", "name": "Moroccan" },
  { "symbol": "MOZ", "name": "Mozambican" },
  { "symbol": "MMR", "name": "Burmese" },
  { "symbol": "NAM", "name": "Namibian" },
  { "symbol": "NRU", "name": "Nauruan" },
  { "symbol": "NPL", "name": "Nepalese" },
  { "symbol": "NLD", "name": "Dutch" },
  { "symbol": "NCL", "name": "New Caledonian" },
  { "symbol": "NZL", "name": "New Zealand" },
  { "symbol": "NIC", "name": "Nicaraguan" },
  { "symbol": "NER", "name": "Nigerien" },
  { "symbol": "NGA", "name": "Nigerian" },
  { "symbol": "NIU", "name": "Niuean" },
  { "symbol": "NFK", "name": "Norfolk Islander" },
  { "symbol": "MNP", "name": "Northern Mariana Islander" },
  { "symbol": "NOR", "name": "Norwegian" },
  { "symbol": "OMN", "name": "Omani" },
  { "symbol": "PAK", "name": "Pakistani" },
  { "symbol": "PLW", "name": "Palauan" },
  { "symbol": "PSE", "name": "Palestinian" },
  { "symbol": "PAN", "name": "Panamanian" },
  { "symbol": "PNG", "name": "Papua New Guinean" },
  { "symbol": "PRY", "name": "Paraguayan" },
  { "symbol": "PER", "name": "Peruvian" },
  { "symbol": "PHL", "name": "Filipino" },
  { "symbol": "PCN", "name": "Pitcairn Islander" },
  { "symbol": "POL", "name": "Polish" },
  { "symbol": "PRT", "name": "Portuguese" },
  { "symbol": "PRI", "name": "Puerto Rican" },
  { "symbol": "QAT", "name": "Qatari" },
  { "symbol": "REU", "name": "Réunionese" },
  { "symbol": "ROU", "name": "Romanian" },
  { "symbol": "RUS", "name": "Russian" },
  { "symbol": "RWA", "name": "Rwandan" },
  { "symbol": "BLM", "name": "Saint Barthélemy" },
  { "symbol": "SHN", "name": "Saint Helenian" },
  { "symbol": "KNA", "name": "Kittitian" },
  { "symbol": "LCA", "name": "Saint Lucian" },
  { "symbol": "MAF", "name": "Saint Martin" },
  { "symbol": "SPM", "name": "Saint Pierre and Miquelon" },
  { "symbol": "VCT", "name": "Saint Vincentian" },
  { "symbol": "WSM", "name": "Samoan" },
  { "symbol": "SMR", "name": "Sammarinese" },
  { "symbol": "STP", "name": "Sao Tomean" },
  { "symbol": "SAU", "name": "Saudi" },
  { "symbol": "SEN", "name": "Senegalese" },
  { "symbol": "SRB", "name": "Serbian" },
  { "symbol": "SYC", "name": "Seychellois" },
  { "symbol": "SLE", "name": "Sierra Leonean" },
  { "symbol": "SGP", "name": "Singaporean" },
  { "symbol": "SXM", "name": "Sint Maarten" },
  { "symbol": "SVK", "name": "Slovak" },
  { "symbol": "SVN", "name": "Slovenian" },
  { "symbol": "SLB", "name": "Solomon Islander" },
  { "symbol": "SOM", "name": "Somali" },
  { "symbol": "ZAF", "name": "South African" },
  { "symbol": "SGS", "name": "South Georgia" },
  { "symbol": "SSD", "name": "South Sudanese" },
  { "symbol": "ESP", "name": "Spanish" },
  { "symbol": "LKA", "name": "Sri Lankan" },
  { "symbol": "SDN", "name": "Sudanese" },
  { "symbol": "SUR", "name": "Surinamese" },
  { "symbol": "SJM", "name": "Svalbard" },
  { "symbol": "SWE", "name": "Swedish" },
  { "symbol": "CHE", "name": "Swiss" },
  { "symbol": "SYR", "name": "Syrian" },
  { "symbol": "TWN", "name": "Taiwanese" },
  { "symbol": "TJK", "name": "Tajikistani" },
  { "symbol": "TZA", "name": "Tanzanian" },
  { "symbol": "THA", "name": "Thai" },
  { "symbol": "TLS", "name": "East Timorese" },
  { "symbol": "TGO", "name": "Togolese" },
  { "symbol": "TKL", "name": "Tokelauan" },
  { "symbol": "TON", "name": "Tongan" },
  { "symbol": "TTO", "name": "Trinidadian" },
  { "symbol": "TUN", "name": "Tunisian" },
  { "symbol": "TUR", "name": "Turkish" },
  { "symbol": "TKM", "name": "Turkmen" },
  { "symbol": "TCA", "name": "Turks and Caicos Islander" },
  { "symbol": "TUV", "name": "Tuvaluan" },
  { "symbol": "UGA", "name": "Ugandan" },
  { "symbol": "UKR", "name": "Ukrainian" },
  { "symbol": "ARE", "name": "Emirati" },
  { "symbol": "GBR", "name": "British" },
  { "symbol": "USA", "name": "American" },
  { "symbol": "UMI", "name": "U.S. Minor Outlying Islander" },
  { "symbol": "URY", "name": "Uruguayan" },
  { "symbol": "UZB", "name": "Uzbekistani" },
  { "symbol": "VUT", "name": "Vanuatuan" },
  { "symbol": "VEN", "name": "Venezuelan" },
  { "symbol": "VNM", "name": "Vietnamese" },
  { "symbol": "VGB", "name": "British Virgin Islander" },
  { "symbol": "VIR", "name": "U.S. Virgin Islander" },
  { "symbol": "WLF", "name": "Wallis and Futuna Islander" },
  { "symbol": "ESH", "name": "Sahrawi" },
  { "symbol": "YEM", "name": "Yemeni" },
  { "symbol": "ZMB", "name": "Zambian" },
  { "symbol": "ZWE", "name": "Zimbabwean" }
]